AUTHORS.rst
CONTRIBUTING.rst
HISTORY.rst
MANIFEST.in
README.rst
pyproject.toml
docs/Makefile
docs/authors.rst
docs/conf.py
docs/contributing.rst
docs/history.rst
docs/index.rst
docs/installation.rst
docs/make.bat
docs/readme.rst
docs/usage.rst
src/veriframe/__init__.py
src/veriframe/cli.py
src/veriframe/defaults.yml
src/veriframe/regression.py
src/veriframe/stats.py
src/veriframe/taylor.py
src/veriframe/vardef.yml
src/veriframe/veriframe.py
src/veriframe/verisat.py
src/veriframe.egg-info/PKG-INFO
src/veriframe.egg-info/SOURCES.txt
src/veriframe.egg-info/dependency_links.txt
src/veriframe.egg-info/requires.txt
src/veriframe.egg-info/top_level.txt
tests/__init__.py
tests/test_stats.py
tests/test_veriframe.py
tests/test_verisat.py
tests/data/colocs.csv
tests/data/baltic.zarr/.zattrs
tests/data/baltic.zarr/.zgroup
tests/data/baltic.zarr/.zmetadata
tests/data/baltic.zarr/depth/.zarray
tests/data/baltic.zarr/depth/.zattrs
tests/data/baltic.zarr/depth/0.0.0
tests/data/baltic.zarr/depth/0.0.1
tests/data/baltic.zarr/hs/.zarray
tests/data/baltic.zarr/hs/.zattrs
tests/data/baltic.zarr/hs/0.0.0
tests/data/baltic.zarr/hs/0.0.1
tests/data/baltic.zarr/latitude/.zarray
tests/data/baltic.zarr/latitude/.zattrs
tests/data/baltic.zarr/latitude/0
tests/data/baltic.zarr/longitude/.zarray
tests/data/baltic.zarr/longitude/.zattrs
tests/data/baltic.zarr/longitude/0
tests/data/baltic.zarr/time/.zarray
tests/data/baltic.zarr/time/.zattrs
tests/data/baltic.zarr/time/0