Metadata-Version: 2.4
Name: veriframe
Version: 0.3.0
Summary: Dataframe for model verification
Author-email: Oceanum Developers <developers@oceanum.science>
Maintainer-email: Oceanum Developers <developers@oceanum.science>
License: Not open source
Project-URL: bugs, https://github.com/oceanum/veriframe/issues
Project-URL: changelog, https://github.com/oceanum/veriframe/blob/master/changelog.md
Project-URL: homepage, https://github.com/oceanum/veriframe
License-File: AUTHORS.rst
Requires-Dist: cartopy
Requires-Dist: geopandas
Requires-Dist: matplotlib
Requires-Dist: pyyaml
Requires-Dist: rompy
Requires-Dist: scipy
Requires-Dist: tabulate
Requires-Dist: typer
Requires-Dist: xarray
Provides-Extra: dev
Requires-Dist: coverage; extra == "dev"
Requires-Dist: mypy; extra == "dev"
Requires-Dist: pytest; extra == "dev"
Requires-Dist: ruff; extra == "dev"
Requires-Dist: sphinx; extra == "dev"
Requires-Dist: tox; extra == "dev"
Requires-Dist: twine; extra == "dev"
Dynamic: license-file
